<?xml version="1.0" encoding="UTF-8"?>
<objects serializationModel="Studio.02.03.00">
	<object class="AudioFile" id="{dce8a95b-ac5f-4fd5-9e6f-4e5e66a45856}">
		<property name="assetPath">
			<value>SFX/Battle/Sheath/Shealth_Weapon_Decline_Attack.wav</value>
		</property>
		<property name="frequencyInKHz">
			<value>44.0999985</value>
		</property>
		<property name="channelCount">
			<value>2</value>
		</property>
		<property name="length">
			<value>1.090249433106576</value>
		</property>
		<relationship name="masterAssetFolder">
			<destination>{2f21a3fc-c3d9-4fa2-adf4-b887d0596e26}</destination>
		</relationship>
	</object>
</objects>
